alpacloud_ansible_builder.py
alpacloud_ansible_builder-0.1.3.dist-info/METADATA
alpacloud_ansible_builder-0.1.3.dist-info/WHEEL
alpacloud_ansible_builder-0.1.3.dist-info/entry_points.txt
alpacloud_ansible_builder-0.1.3.dist-info/top_level.txt
alpacloud_ansible_builder-0.1.3.dist-info/RECORD
