Metadata-Version: 2.1
Name: alpacloud-ansible-builder
Version: 0.1.3
Summary: This tool automatically builds and installs Ansible Collections
Home-page: https://github.com/lilatomic/alpacloud
Author: lilatomic
License: UNKNOWN
Project-URL: Bug Tracker, https://github.com/lilatomic/alpacloud/issues
Platform: UNKNOWN
Requires-Dist: click (<9,>=7)
Requires-Dist: structlog (~=21.1)
Requires-Dist: watchdog (~=2.0)
Requires-Dist: pyyaml (~=6.0)
